[
    {
        "categoryId":"codereview101_inputValidation",
        "categoryName":"Input Validation",
        "categoryDetails":"categoryInputValidation.md",
        "questions":[
            {
                "questionId":"inputValidation.q1",
                "language":"java",
                "lineToHighlight":3,
                "question":"Which of the following code snippets prevents a vulnerability?",
                "snippets":[
                    "snipInputValidation1.java",
                    "snipInputValidation2.java"
                ],
                "answer":1,
                "correctReasoning":"You're right!",
                "incorrectReasoning": "Incorrect!"
            }
        ]

    },

    {
        "categoryId":"codereview101_paramStatements",
        "categoryName":"Parameterized Statements",
        "categoryDetails":"categoryParamStatements.md",
        "questions":[
            {
                "questionId":"paramStatements.q1",
                "language":"java",
                "lineToHighlight":7,
                "question":"Which of the following code snippets prevents a SQL INJECTION?",
                "snippets":[
                    "snipParamStatements5.java",
                    "snipParamStatements6.java"
                ],
                "answer":0,
                "correctReasoning":"You're right!",
                "incorrectReasoning": "Incorrect!"
            },
            {
                "questionId":"paramStatements.q2",
                "language":"java",
                "lineToHighlight":9,
                "question":"Which of the following code snippets allows an OS COMMAND INJECTION?",
                "snippets":[
                    "snipParamStatements7.java",
                    "snipParamStatements8.java"
                ],
                "answer":0,
                "correctReasoning":"You're right!",
                "incorrectReasoning": "Incorrect!"
            },
            {
                "questionId":"paramStatements.q3",
                "language":"java",
                "lineToHighlight":2,
                "question":"Which of the following code snippets prevents OS COMMAND INJECTION?",
                "snippets":[
                    "snipParamStatements9.java",
                    "snipParamStatements10.java"
                ],
                "answer":0,
                "correctReasoning":"You're right!",
                "incorrectReasoning": "Incorrect!"
            },
            {
                "questionId":"paramStatements.q4",
                "language":"java",
                "lineToHighlight":6,
                "question":"Which of the following code snippets prevents a SQL INJECTION?",
                "snippets":[
                    "snipParamStatements11.java",
                    "snipParamStatements12.java"
                ],
                "answer":1,
                "correctReasoning":"You're right!",
                "incorrectReasoning": "Incorrect!"
            }
        ]

    },

    {
        "categoryId":"codereview101_brokenAuthentication",
        "categoryName":"Broken authentication and Session management",
        "categoryDetails":"categoryBrokenAuthentication.md",
        "questions":[
            {
                "questionId":"brokenAuthentication.q1",
                "language":"java",
                "lineToHighlight":4,
                "question":"Which of the following code snippets is the secure way to authenticate a user password?",
                "snippets":[
                    "snipBrokenAuth1.java",
                    "snipBrokenAuth2.java"
                ],
                "answer":1,
                "correctReasoning":"You're right!",
                "incorrectReasoning": "Incorrect!"
            },
            {
                "questionId":"brokenAuthentication.q2",
                "language":"java",
                "lineToHighlight":4,
                "question":"Which of the following code snippets creates a secure session token?",
                "snippets":[
                    "snipBrokenAuth3.java",
                    "snipBrokenAuth4.java"
                ],
                "answer":1,
                "correctReasoning":"You're right!",
                "incorrectReasoning": "Incorrect!"
            },
            {
                "questionId":"brokenAuthentication.q3",
                "language":"java",
                "lineToHighlight":4,
                "question":"Which of the following code snippets is an insecure way to authenticate a user?",
                "snippets":[
                    "snipBrokenAuth5.java",
                    "snipBrokenAuth6.java"
                ],
                "answer":1,
                "correctReasoning":"You're right!",
                "incorrectReasoning": "Incorrect!"
            },
            {
                "questionId":"brokenAuthentication.q4",
                "language":"java",
                "lineToHighlight":4,
                "question":"Which of the following code snippets uses a secure session token?",
                "snippets":[
                    "snipBrokenAuth7.java",
                    "snipBrokenAuth8.java"
                ],
                "answer":1,
                "correctReasoning":"You're right!",
                "incorrectReasoning": "Incorrect!"
            }
        ]

    },

    {
        "categoryId":"codereview101_memory",
        "categoryName":"Memory Best Practices",
        "categoryDetails":"categoryMemory.md",
        "questions":[
            {
                "questionId":"memory.q1",
                "lineToHighlight":3,
                "language":"C++",
                "question":"Which of the following code snippets prevents a Buffer Overflow vulnerability?",
                "snippets":[
                    "snipMemory1.cpp",
                    "snipMemory2.cpp"
                ],
                "answer":0,
                "correctReasoning":"You're right!",
                "incorrectReasoning": "Incorrect!"
            },

            {
                "questionId":"memory.q2",
                "lineToHighlight":3,
                "language":"C++",
                "question":"Which of the following code snippets employs a best practice to avoid the Incorrect Calculation of Buffer Size?",
                "snippets":[
                    "snipMemory3.cpp",
                    "snipMemory4.cpp"
                ],
                "answer":0,
                "correctReasoning":"You're right!",
                "incorrectReasoning": "Incorrect!"
            },

            {
                "questionId":"memory.q3",
                "lineToHighlight":7,
                "language":"C++",
                "question":"Off-by-one is introduced when employing incorrect comparison operators. Which snippet prevents this type of flaw?",
                "snippets":[
                    "snipMemory5.cpp",
                    "snipMemory6.cpp"
                ],
                "answer":1,
                "correctReasoning":"You're right!",
                "incorrectReasoning": "Incorrect!"
            },

            {
                "questionId":"memory.q4",
                "lineToHighlight":7,
                "language":"C++",
                "question":"Format String Injection is a type of vulnerability caused by concatenating or using user input in a format parameter. Which snippet avoids the vulnerability?",
                "snippets":[
                    "snipMemory7.cpp",
                    "snipMemory8.cpp"
                ],
                "answer":1,
                "correctReasoning":"You're right!",
                "incorrectReasoning": "Incorrect!"
            }
        ]

    },

    {
        "categoryId":"codereview101_data",
        "categoryName":"Protecting Data",
        "categoryDetails":"categoryData.md",
        "questions":[
            {
                "questionId":"data.q1",
                "lineToHighlight":6,
                "language":"java",
                "question":"Which of the following code snippets indicates that the password is stored correctly?",
                "snippets":[
                    "snipData1.java",
                    "snipData2.java"
                ],
                "answer":1,
                "correctReasoning":"You're right!",
                "incorrectReasoning": "Incorrect!"
            },

            {
                "questionId":"data.q2",
                "lineToHighlight":2,
                "language":"java",
                "question":"Can you spot the code that transmits data securely?",
                "snippets":[
                    "snipData3.java",
                    "snipData4.java"
                ],
                "answer":0,
                "correctReasoning":"You're right!",
                "incorrectReasoning": "Incorrect!"
            },

            {
                "questionId":"data.q3",
                "lineToHighlight":2,
                "language":"javascript",
                "question":"Can you spot the code that anonymizes and encrypts the data?",
                "snippets":[
                    "snipData5.js",
                    "snipData6.js"
                ],
                "answer":1,
                "correctReasoning":"You're right!",
                "incorrectReasoning": "Incorrect!"
            }
        ]

    },
    {
        "categoryId":"codereview101_xss",
        "categoryName":"Preventing Cross-Site Scripting",
        "categoryDetails":"categoryXSS.md",
        "questions":[
            {
                "questionId":"xss.q1",
                "language":"html",
                "lineToHighlight":8,
                "question":"Which of the following code snippets prevents XSS through HTML Encoding?",
                "snippets":[
                    "snipXSS1.jsp",
                    "snipXSS2.jsp"
                ],
                "answer":0,
                "correctReasoning":"You're right!",
                "incorrectReasoning": "Incorrect!"
            },

            {
                "questionId":"xss.q2",
                "language":"html",
                "lineToHighlight":4,
                "question":"Both code samples use HTML Encoding but which one uses the correct encoding for the output context?",
                "snippets":[
                    "snipXSS3.jsp",
                    "snipXSS4.jsp"
                ],
                "answer":0,
                "correctReasoning":"You're right!",
                "incorrectReasoning": "Incorrect!"
            },

            {
                "questionId":"xss.q3",
                "language":"javascript",
                "lineToHighlight":8,
                "question":"In this case the application is implementing its own client side rendering of the input instead of taking advantage of a JS framework. Can you tell which snippet is safer?",
                "snippets":[
                    "snipXSS5.js",
                    "snipXSS6.js"
                ],
                "answer":0,
                "correctReasoning":"You're right!",
                "incorrectReasoning": "Incorrect!"
            },

            {
                "questionId":"xss.q4",
                "language":"javascript",
                "lineToHighlight":7,
                "question":"The following example is showing the use of a JavaScript parameterized statement. Can you spot the snippet that leverages this best practice?",
                "snippets":[
                    "snipXSS7.js",
                    "snipXSS8.js"
                ],
                "answer":1,
                "correctReasoning":"You're right!",
                "incorrectReasoning": "Incorrect!"
            },

            {
                "questionId": "xss.q5",
                "language": "javascript",
                "lineToHighlight": 5,
                "question": "In the following React example, which of the code snippets prevents XSS?",
                "snippets": [
                    "snipXSS9.jsx",
                    "snipXSS10.jsx"
                ],
                "answer": 1,
                "correctReasoning": "You're right!",
                "incorrectReasoning": "Incorrect!"
            }
        ]

    },

    {
        "categoryId":"codereview101_indirectReferences",
        "categoryName":"Indirect Object References",
        "categoryDetails":"categoryIndirectReferences.md",
        "questions":[
            {
                "questionId":"indirectReferences.q1",
                "language":"java",
                "lineToHighlight":3,
                "question":"Which of the following code snippets prevents Path Traversal?",
                "snippets":[
                    "snipIndirectReferences1.java",
                    "snipIndirectReferences2.java"
                ],
                "answer":1,
                "correctReasoning":"You're right!",
                "incorrectReasoning": "Incorrect!"
            },

            {
                "questionId":"indirectReferences.q2",
                "language":"java",
                "lineToHighlight":2,
                "question":"Which of the following code snippets prevents Open Redirect?",
                "snippets":[
                    "snipIndirectReferences3.java",
                    "snipIndirectReferences4.java"
                ],
                "answer":1,
                "correctReasoning":"You're right!",
                "incorrectReasoning": "Incorrect!"
            }
        ]

    }

]
